{
  "version": "7",
  "dialect": "postgresql",
  "entries": [
    {
      "idx": 0,
      "version": "7",
      "when": 1781736426494,
      "tag": "0000_illegal_harpoon",
      "breakpoints": true
    },
    {
      "idx": 1,
      "version": "7",
      "when": 1781740894380,
      "tag": "0001_smart_cerebro",
      "breakpoints": true
    },
    {
      "idx": 2,
      "version": "7",
      "when": 1781742898564,
      "tag": "0002_amazing_klaw",
      "breakpoints": true
    },
    {
      "idx": 3,
      "version": "7",
      "when": 1781753532536,
      "tag": "0003_clever_whistler",
      "breakpoints": true
    }
  ]
}